fetch_unit_with_btb.v
module fetch_unit_with_btb (
    input clk,
    input reset,
    input stall,
    input flush,
    input branch_taken_execute,        // Actual branch behavior from Execute stage
    input [31:0] pc_execute,           // Branch instruction address from Execute stage
    input [31:0] target_pc_execute,    // Target address from Execute stage
    output reg [31:0] pc_out,          // Next PC for Fetch stage
    output reg btb_hit,                // BTB hit signal
    output reg [31:0] predicted_pc     // Predicted PC signal
);

    // BTB Parameters
    localparam NUM_SETS = 16;          // Number of sets (index bits are [5:2])
    localparam NUM_WAYS = 4;           // Number of ways per set

    // Predictor states
    localparam STRONGLY_NOT_TAKEN = 2'b00;
    localparam WEAKLY_NOT_TAKEN   = 2'b01;
    localparam WEAKLY_TAKEN       = 2'b10;
    localparam STRONGLY_TAKEN     = 2'b11;

    // BTB: 4-Way Associative
    reg [27:0] btb_tag [NUM_SETS-1:0][NUM_WAYS-1:0];         // Tag bits (upper PC bits)
    reg [31:0] btb_target_pc [NUM_SETS-1:0][NUM_WAYS-1:0];   // Target PC
    reg [1:0] btb_predictor [NUM_SETS-1:0][NUM_WAYS-1:0];    // 2-bit saturating counter
    reg btb_valid [NUM_SETS-1:0][NUM_WAYS-1:0];              // Valid bit
    reg [1:0] fifo_pointer [NUM_SETS-1:0];                   // FIFO queue pointer for replacement

    // Current PC
    reg [31:0] current_pc;

    // Internal Signals
    wire [3:0] set_index;              // Index derived from PC(current)
    wire [27:0] tag_bits;              // Tag derived from PC(current)

    // To Extract Set Index and Tag of PC in execute stage
    wire [3:0] set_index_execute;
    wire [27:0] tag_bits_execute;
    assign set_index_execute = pc_execute[5:2]; // Using PC from Execute stage
    assign tag_bits_execute = pc_execute[31:6]; // Tag of PC from Execute stage

    // Extracting Set Index (bits 5 to 2 of PC, skipping the last 2 bits as address size is 32 bits and thus last two bits will always be 00)
    assign set_index = current_pc[5:2];
    // Extracting Tag (remaining upper bits of PC current)
    assign tag_bits = current_pc[31:6];

    // Compute Next PC
    always @(*) begin
        btb_hit = 0;
        predicted_pc = current_pc + 4; // Default next PC is sequential

        // Searching BTB set for a match
        for (integer i = 0; i < NUM_WAYS; i = i + 1) begin
            if (btb_valid[set_index][i] && btb_tag[set_index][i] == tag_bits) begin
                btb_hit = 1;
                if (btb_predictor[set_index][i][1]) // Predictor suggests branch taken
                    predicted_pc = btb_target_pc[set_index][i];
            end
        end
    end

    // Update PC
    always @(posedge clk or posedge reset) begin
        if (reset)
            current_pc <= 32'b0;
        else if (!stall)
            current_pc <= flush ? pc_execute : predicted_pc;
    end

    // Output the current PC
    always @(*) begin
        pc_out = current_pc;
    end

    // Updating BTB on Branch Resolution
    always @(posedge clk or posedge reset) begin
        if (reset) begin
            // Invalidate all BTB entries and reset FIFO pointers
            for (integer set = 0; set < NUM_SETS; set = set + 1) begin
                for (integer way = 0; way < NUM_WAYS; way = way + 1) begin
                    btb_valid[set][way] <= 0;
                end
                fifo_pointer[set] <= 0;
            end
        end else if (branch_taken_execute || flush) begin  // If branch was taken actually or there was a pipeline flush due to misprediction
            // Check for an existing entry in the BTB set
            integer i, replace_way;
            reg found;
            found = 0;
            for (i = 0; i < NUM_WAYS; i = i + 1) begin
                if (btb_valid[set_index_execute][i] && btb_tag[set_index_execute][i] == tag_bits_execute) begin

                    // Update existing BTB entry only if moving between weakly taken and weakly not taken
                    if ((btb_predictor[set_index_execute][i] == WEAKLY_TAKEN && !branch_taken_execute) ||
                        (btb_predictor[set_index_execute][i] == WEAKLY_NOT_TAKEN && branch_taken_execute)) begin
                        btb_target_pc[set_index_execute][i] <= target_pc_execute;
                    end

                    // Adjust predictor
                    if (branch_taken_execute) begin
                        btb_predictor[set_index_execute][i] <= (btb_predictor[set_index_execute][i] == STRONGLY_TAKEN) ? STRONGLY_TAKEN :
                                                       (btb_predictor[set_index_execute][i] + 1);
                    end else begin
                        btb_predictor[set_index_execute][i] <= (btb_predictor[set_index_execute][i] == STRONGLY_NOT_TAKEN) ? STRONGLY_NOT_TAKEN :
                                                       (btb_predictor[set_index_execute][i] - 1);
                    end
                    found = 1;
                end
            end
            if (!found) begin
                // Replace the FIFO entry
                replace_way = fifo_pointer[set_index_execute];
                btb_tag[set_index_execute][replace_way] <= tag_bits_execute;
                btb_target_pc[set_index_execute][replace_way] <= target_pc_execute;
                btb_predictor[set_index_execute][replace_way] <= branch_taken_execute ? WEAKLY_TAKEN : WEAKLY_NOT_TAKEN;
                // Validating the entry
                btb_valid[set_index_execute][replace_way] <= 1;
                // Update FIFO pointer
                fifo_pointer[set_index_execute] <= (fifo_pointer[set_index_execute] + 1) % NUM_WAYS;
            end
        end
    end
endmodule

tb_1loop.v
module tb_1loop;

    // Testbench Parameters
    localparam N = 11; // Number of iterations of loop
    localparam CLK_PERIOD = 10;

    // Testbench Signals
    reg clk, reset, stall, flush;
    reg branch_taken_execute;
    reg [31:0] pc_execute, target_pc_execute;
    wire [31:0] pc_out;
    wire btb_hit;
    wire [31:0] predicted_pc;

    // Instantiate the DUT
    fetch_unit_with_btb dut (
        .clk(clk),
        .reset(reset),
        .stall(stall),
        .flush(flush),
        .branch_taken_execute(branch_taken_execute),
        .pc_execute(pc_execute),
        .target_pc_execute(target_pc_execute),
        .pc_out(pc_out),
        .btb_hit(btb_hit),
        .predicted_pc(predicted_pc)
    );

    // Simulation Variables
    reg [31:0] loop_start_pc = 32'h00000004; // Start of loop
    reg [31:0] loop_end_pc = 32'h00000014;   // End of loop
    reg [31:0] loop_target_pc = 32'h00000004; // Target of branch
    reg [31:0] current_pc;

    integer correct_predictions = 0, total_predictions = 0; // total predictions indicate predictions due to btb hit
    integer total_instructions = 0, total_branch_instructions = 0;

    // Clock Generation
    always #(CLK_PERIOD / 2) clk = ~clk;

    // Test Sequence
    initial begin

        // Enable VCD Dump
        $dumpfile("tb_1loop.vcd"); 
        $dumpvars(0, tb_1loop);  

        // Initialize Signals
        clk = 0; reset = 1; stall = 0; flush = 0;
        branch_taken_execute = 0; pc_execute = 0; target_pc_execute = 0;

        // Deassert Reset
        #(CLK_PERIOD) reset = 0;

        // Simulate Instruction Execution
        current_pc = 32'b0;

        while (current_pc != loop_end_pc + 4) begin
            // Fetch Stage
            if (!stall) begin
                total_instructions = total_instructions + 1;

                // Simulate Branch Instruction
                if (current_pc == loop_end_pc) begin
                    total_branch_instructions = total_branch_instructions + 1;

                    // Condition for loop branch: loop back until exit condition
                    branch_taken_execute = (total_branch_instructions <= N);
                    pc_execute = current_pc;
                    target_pc_execute = branch_taken_execute ? loop_target_pc : loop_end_pc + 4;

                    // Check BTB prediction
                    if (btb_hit) begin
                        if ((branch_taken_execute && predicted_pc == target_pc_execute) ||
                            (!branch_taken_execute && predicted_pc == pc_execute + 4)) begin
                            correct_predictions = correct_predictions + 1;
                        end
                    end

                    flush = 1; // Flushing everytime so that in case there was wrong prediction our pc gets updated properly and ahead results are analysed properly
                    #(CLK_PERIOD);
                    flush = 0;

                    current_pc = branch_taken_execute ? target_pc_execute : loop_end_pc + 4;
                end else begin
                    branch_taken_execute = 0;
                    current_pc = current_pc + 4; // Sequential execution
                end
            end

            // Update BTB (happens internally in the DUT)
            #(CLK_PERIOD);
            if (btb_hit) begin
                // If there was  a btb hit that means we are predicting pc referring to btb table
                total_predictions = total_predictions + 1;
            end

            // Continuous Monitoring after each instruction execution
            $display("Total Instructions: %0d | Current PC: %0h | Branch Taken: %b | BTB Hit: %b | Predicted PC: %0h | Correct Predictions: %0d | Total Predictions: %0d",
                     total_instructions, current_pc, branch_taken_execute, btb_hit, predicted_pc, correct_predictions, total_predictions);

        end


        // Display Results
        $display("Simulation Results:");
        $display("-------------------");
        $display("Total Instructions        : %0d", total_instructions);
        $display("Total Branch Instructions : %0d", total_branch_instructions);
        $display("Total Predictions         : %0d", total_predictions);
        $display("Correct Predictions       : %0d", correct_predictions);
        $display("Prediction Accuracy       : %0.2f%%",
                 (total_predictions > 0) ? (correct_predictions * 100.0 / total_branch_instructions) : 0.0);
        $display("BTB Hit Rate              : %0.2f%%",
                 (total_predictions > 0) ? (total_predictions * 100.0 / total_branch_instructions) : 0.0);

        // End Simulation
        $stop;
    end

endmodule

tb_1loop.vcd
$date
	Sun Nov 24 23:45:10 2024
$end
$version
	Icarus Verilog
$end
$timescale
	1s
$end
$scope module tb_1loop $end
$var wire 32 ! predicted_pc [31:0] $end
$var wire 32 " pc_out [31:0] $end
$var wire 1 # btb_hit $end
$var parameter 32 $ CLK_PERIOD $end
$var parameter 32 % N $end
$var reg 1 & branch_taken_execute $end
$var reg 1 ' clk $end
$var reg 32 ( current_pc [31:0] $end
$var reg 1 ) flush $end
$var reg 32 * loop_end_pc [31:0] $end
$var reg 32 + loop_start_pc [31:0] $end
$var reg 32 , loop_target_pc [31:0] $end
$var reg 32 - pc_execute [31:0] $end
$var reg 1 . reset $end
$var reg 1 / stall $end
$var reg 32 0 target_pc_execute [31:0] $end
$var integer 32 1 correct_predictions [31:0] $end
$var integer 32 2 total_branch_instructions [31:0] $end
$var integer 32 3 total_instructions [31:0] $end
$var integer 32 4 total_predictions [31:0] $end
$scope module dut $end
$var wire 1 & branch_taken_execute $end
$var wire 1 ' clk $end
$var wire 1 ) flush $end
$var wire 32 5 pc_execute [31:0] $end
$var wire 1 . reset $end
$var wire 1 / stall $end
$var wire 32 6 target_pc_execute [31:0] $end
$var wire 28 7 tag_bits_execute [27:0] $end
$var wire 28 8 tag_bits [27:0] $end
$var wire 4 9 set_index_execute [3:0] $end
$var wire 4 : set_index [3:0] $end
$var parameter 32 ; NUM_SETS $end
$var parameter 32 < NUM_WAYS $end
$var parameter 2 = STRONGLY_NOT_TAKEN $end
$var parameter 2 > STRONGLY_TAKEN $end
$var parameter 2 ? WEAKLY_NOT_TAKEN $end
$var parameter 2 @ WEAKLY_TAKEN $end
$var reg 1 # btb_hit $end
$var reg 32 A current_pc [31:0] $end
$var reg 32 B pc_out [31:0] $end
$var reg 32 C predicted_pc [31:0] $end
$scope begin $ivl_for_loop0 $end
$var integer 32 D i [31:0] $end
$upscope $end
$scope begin $ivl_for_loop1 $end
$var integer 32 E set [31:0] $end
$scope begin $ivl_for_loop2 $end
$var integer 32 F way [31:0] $end
$upscope $end
$upscope $end
$scope begin $unm_blk_18 $end
$var reg 1 G found $end
$var integer 32 H i [31:0] $end
$var integer 32 I replace_way [31:0] $end
$upscope $end
$upscope $end
$upscope $end
$enddefinitions $end
$comment Show the parameter values. $end
$dumpall
b10 @
b1 ?
b11 >
b0 =
b100 <
b10000 ;
b1011 %
b1010 $
$end
#0
$dumpvars
bx I
bx H
xG
b100 F
b10000 E
b100 D
b100 C
b0 B
b0 A
b0 :
b0 9
b0 8
b0 7
b0 6
b0 5
b0 4
b0 3
b0 2
b0 1
b0 0
0/
1.
b0 -
b100 ,
b100 +
b10100 *
0)
bx (
0'
0&
0#
b0 "
b100 !
$end
#5
b100 F
b10000 E
1'
#10
0'
b1 3
b100 (
0.
#15
b100 "
b100 B
b100 D
b1000 !
b1000 C
b1 :
b100 A
1'
#20
0'
b1000 (
b10 3
#25
b1000 "
b1000 B
b100 D
b1100 !
b1100 C
b10 :
b1000 A
1'
#30
0'
b1100 (
b11 3
#35
b1100 "
b1100 B
b100 D
b10000 !
b10000 C
b11 :
b1100 A
1'
#40
0'
b10000 (
b100 3
#45
b10000 "
b10000 B
b100 D
b10100 !
b10100 C
b100 :
b10000 A
1'
#50
0'
b10100 (
b101 3
#55
b10100 "
b10100 B
b100 D
b11000 !
b11000 C
b101 :
b10100 A
1'
#60
b101 9
0'
1)
b100 0
b100 6
b10100 -
b10100 5
1&
b1 2
b110 3
#65
b100 !
b100 C
1#
b100 D
b0 I
b100 H
0G
1'
#70
0'
b100 (
0)
#75
b100 "
b100 B
b100 D
b1000 !
b1000 C
0#
b1 :
b100 A
1G
b100 H
1'
#80
0'
b1000 (
0&
b111 3
#85
b1000 "
b1000 B
b100 D
b1100 !
b1100 C
b10 :
b1000 A
1'
#90
0'
b1100 (
b1000 3
#95
b1100 "
b1100 B
b100 D
b10000 !
b10000 C
b11 :
b1100 A
1'
#100
0'
b10000 (
b1001 3
#105
b10000 "
b10000 B
b100 D
b10100 !
b10100 C
b100 :
b10000 A
1'
#110
0'
b10100 (
b1010 3
#115
b10100 "
b10100 B
1#
b100 D
b100 !
b100 C
b101 :
b10100 A
1'
#120
0'
1)
b1 1
1&
b10 2
b1011 3
b1 4
#125
b100 H
1G
1'
#130
0'
b100 (
0)
#135
b100 "
b100 B
b100 D
b1000 !
b1000 C
0#
b1 :
b100 A
b100 H
1G
1'
#140
0'
b1000 (
0&
b1100 3
#145
b1000 "
b1000 B
b100 D
b1100 !
b1100 C
b10 :
b1000 A
1'
#150
0'
b1100 (
b1101 3
#155
b1100 "
b1100 B
b100 D
b10000 !
b10000 C
b11 :
b1100 A
1'
#160
0'
b10000 (
b1110 3
#165
b10000 "
b10000 B
b100 D
b10100 !
b10100 C
b100 :
b10000 A
1'
#170
0'
b10100 (
b1111 3
#175
b10100 "
b10100 B
1#
b100 D
b100 !
b100 C
b101 :
b10100 A
1'
#180
0'
1)
b10 1
1&
b11 2
b10000 3
b10 4
#185
b100 H
1G
1'
#190
0'
b100 (
0)
#195
b100 "
b100 B
b100 D
b1000 !
b1000 C
0#
b1 :
b100 A
b100 H
1G
1'
#200
0'
b1000 (
0&
b10001 3
#205
b1000 "
b1000 B
b100 D
b1100 !
b1100 C
b10 :
b1000 A
1'
#210
0'
b1100 (
b10010 3
#215
b1100 "
b1100 B
b100 D
b10000 !
b10000 C
b11 :
b1100 A
1'
#220
0'
b10000 (
b10011 3
#225
b10000 "
b10000 B
b100 D
b10100 !
b10100 C
b100 :
b10000 A
1'
#230
0'
b10100 (
b10100 3
#235
b10100 "
b10100 B
1#
b100 D
b100 !
b100 C
b101 :
b10100 A
1'
#240
0'
1)
b11 1
1&
b100 2
b10101 3
b11 4
#245
b100 H
1G
1'
#250
0'
b100 (
0)
#255
b100 "
b100 B
b100 D
b1000 !
b1000 C
0#
b1 :
b100 A
b100 H
1G
1'
#260
0'
b1000 (
0&
b10110 3
#265
b1000 "
b1000 B
b100 D
b1100 !
b1100 C
b10 :
b1000 A
1'
#270
0'
b1100 (
b10111 3
#275
b1100 "
b1100 B
b100 D
b10000 !
b10000 C
b11 :
b1100 A
1'
#280
0'
b10000 (
b11000 3
#285
b10000 "
b10000 B
b100 D
b10100 !
b10100 C
b100 :
b10000 A
1'
#290
0'
b10100 (
b11001 3
#295
b10100 "
b10100 B
1#
b100 D
b100 !
b100 C
b101 :
b10100 A
1'
#300
0'
1)
b100 1
1&
b101 2
b11010 3
b100 4
#305
b100 H
1G
1'
#310
0'
b100 (
0)
#315
b100 "
b100 B
b100 D
b1000 !
b1000 C
0#
b1 :
b100 A
b100 H
1G
1'
#320
0'
b1000 (
0&
b11011 3
#325
b1000 "
b1000 B
b100 D
b1100 !
b1100 C
b10 :
b1000 A
1'
#330
0'
b1100 (
b11100 3
#335
b1100 "
b1100 B
b100 D
b10000 !
b10000 C
b11 :
b1100 A
1'
#340
0'
b10000 (
b11101 3
#345
b10000 "
b10000 B
b100 D
b10100 !
b10100 C
b100 :
b10000 A
1'
#350
0'
b10100 (
b11110 3
#355
b10100 "
b10100 B
1#
b100 D
b100 !
b100 C
b101 :
b10100 A
1'
#360
0'
1)
b101 1
1&
b110 2
b11111 3
b101 4
#365
b100 H
1G
1'
#370
0'
b100 (
0)
#375
b100 "
b100 B
b100 D
b1000 !
b1000 C
0#
b1 :
b100 A
b100 H
1G
1'
#380
0'
b1000 (
0&
b100000 3
#385
b1000 "
b1000 B
b100 D
b1100 !
b1100 C
b10 :
b1000 A
1'
#390
0'
b1100 (
b100001 3
#395
b1100 "
b1100 B
b100 D
b10000 !
b10000 C
b11 :
b1100 A
1'
#400
0'
b10000 (
b100010 3
#405
b10000 "
b10000 B
b100 D
b10100 !
b10100 C
b100 :
b10000 A
1'
#410
0'
b10100 (
b100011 3
#415
b10100 "
b10100 B
1#
b100 D
b100 !
b100 C
b101 :
b10100 A
1'
#420
0'
1)
b110 1
1&
b111 2
b100100 3
b110 4
#425
b100 H
1G
1'
#430
0'
b100 (
0)
#435
b100 "
b100 B
b100 D
b1000 !
b1000 C
0#
b1 :
b100 A
b100 H
1G
1'
#440
0'
b1000 (
0&
b100101 3
#445
b1000 "
b1000 B
b100 D
b1100 !
b1100 C
b10 :
b1000 A
1'
#450
0'
b1100 (
b100110 3
#455
b1100 "
b1100 B
b100 D
b10000 !
b10000 C
b11 :
b1100 A
1'
#460
0'
b10000 (
b100111 3
#465
b10000 "
b10000 B
b100 D
b10100 !
b10100 C
b100 :
b10000 A
1'
#470
0'
b10100 (
b101000 3
#475
b10100 "
b10100 B
1#
b100 D
b100 !
b100 C
b101 :
b10100 A
1'
#480
0'
1)
b111 1
1&
b1000 2
b101001 3
b111 4
#485
b100 H
1G
1'
#490
0'
b100 (
0)
#495
b100 "
b100 B
b100 D
b1000 !
b1000 C
0#
b1 :
b100 A
b100 H
1G
1'
#500
0'
b1000 (
0&
b101010 3
#505
b1000 "
b1000 B
b100 D
b1100 !
b1100 C
b10 :
b1000 A
1'
#510
0'
b1100 (
b101011 3
#515
b1100 "
b1100 B
b100 D
b10000 !
b10000 C
b11 :
b1100 A
1'
#520
0'
b10000 (
b101100 3
#525
b10000 "
b10000 B
b100 D
b10100 !
b10100 C
b100 :
b10000 A
1'
#530
0'
b10100 (
b101101 3
#535
b10100 "
b10100 B
1#
b100 D
b100 !
b100 C
b101 :
b10100 A
1'
#540
0'
1)
b1000 1
1&
b1001 2
b101110 3
b1000 4
#545
b100 H
1G
1'
#550
0'
b100 (
0)
#555
b100 "
b100 B
b100 D
b1000 !
b1000 C
0#
b1 :
b100 A
b100 H
1G
1'
#560
0'
b1000 (
0&
b101111 3
#565
b1000 "
b1000 B
b100 D
b1100 !
b1100 C
b10 :
b1000 A
1'
#570
0'
b1100 (
b110000 3
#575
b1100 "
b1100 B
b100 D
b10000 !
b10000 C
b11 :
b1100 A
1'
#580
0'
b10000 (
b110001 3
#585
b10000 "
b10000 B
b100 D
b10100 !
b10100 C
b100 :
b10000 A
1'
#590
0'
b10100 (
b110010 3
#595
b10100 "
b10100 B
1#
b100 D
b100 !
b100 C
b101 :
b10100 A
1'
#600
0'
1)
b1001 1
1&
b1010 2
b110011 3
b1001 4
#605
b100 H
1G
1'
#610
0'
b100 (
0)
#615
b100 "
b100 B
b100 D
b1000 !
b1000 C
0#
b1 :
b100 A
b100 H
1G
1'
#620
0'
b1000 (
0&
b110100 3
#625
b1000 "
b1000 B
b100 D
b1100 !
b1100 C
b10 :
b1000 A
1'
#630
0'
b1100 (
b110101 3
#635
b1100 "
b1100 B
b100 D
b10000 !
b10000 C
b11 :
b1100 A
1'
#640
0'
b10000 (
b110110 3
#645
b10000 "
b10000 B
b100 D
b10100 !
b10100 C
b100 :
b10000 A
1'
#650
0'
b10100 (
b110111 3
#655
b10100 "
b10100 B
1#
b100 D
b100 !
b100 C
b101 :
b10100 A
1'
#660
0'
1)
b1010 1
1&
b1011 2
b111000 3
b1010 4
#665
b100 H
1G
1'
#670
0'
b100 (
0)
#675
b100 "
b100 B
b100 D
b1000 !
b1000 C
0#
b1 :
b100 A
b100 H
1G
1'
#680
0'
b1000 (
0&
b111001 3
#685
b1000 "
b1000 B
b100 D
b1100 !
b1100 C
b10 :
b1000 A
1'
#690
0'
b1100 (
b111010 3
#695
b1100 "
b1100 B
b100 D
b10000 !
b10000 C
b11 :
b1100 A
1'
#700
0'
b10000 (
b111011 3
#705
b10000 "
b10000 B
b100 D
b10100 !
b10100 C
b100 :
b10000 A
1'
#710
0'
b10100 (
b111100 3
#715
b10100 "
b10100 B
1#
b100 D
b100 !
b100 C
b101 :
b10100 A
1'
#720
0'
1)
b11000 0
b11000 6
b1100 2
b111101 3
b1011 4
#725
b100 D
b100 !
b100 C
1#
b100 H
1G
1'
#730
0'
b11000 (
0)
#735
b100 "
b100 B
b100 D
b1000 !
b1000 C
0#
b1 :
b100 A
1'
